gundog/__init__.py
gundog/__main__.py
gundog/_bm25.py
gundog/_chunker.py
gundog/_cli.py
gundog/_config.py
gundog/_daemon.py
gundog/_embedder.py
gundog/_embedder_onnx.py
gundog/_git.py
gundog/_graph.py
gundog/_indexer.py
gundog/_query.py
gundog/_ssl.py
gundog/_templates.py
gundog/_tfidf.py
gundog/_utils.py
gundog/_version.py
gundog/py.typed
gundog/_static/__init__.py
gundog/_static/index.html
gundog/_store/__init__.py
gundog/_store/_base.py
gundog/_store/_hnsw_store.py
gundog/_store/_numpy_store.py
gundog-0.4.1.dist-info/METADATA
gundog-0.4.1.dist-info/WHEEL
gundog-0.4.1.dist-info/entry_points.txt
gundog-0.4.1.dist-info/RECORD
