Metadata-Version: 2.4
Name: gundog
Version: 0.4.1
Summary: A fast semantic search and retrieval engine
Author: ivdi
License-Expression: GPL-3.0-or-later
Classifier: Development Status :: 3 - Alpha
Classifier: Intended Audience :: Developers
Classifier: License :: OSI Approved :: GNU General Public License v3 or later (GPLv3+)
Classifier: Programming Language :: Python :: 3
Classifier: Programming Language :: Python :: 3.12
Classifier: Programming Language :: Python :: 3.13
Requires-Python: >=3.12
Requires-Dist: fastapi>=0.115.0
Requires-Dist: gundog-core>=0.3.1
Requires-Dist: hnswlib>=0.8.0
Requires-Dist: httpx>=0.27.0
Requires-Dist: numpy>=1.24.0
Requires-Dist: onnxruntime>=1.16.0
Requires-Dist: optimum[onnxruntime]>=1.13.0
Requires-Dist: pathspec>=0.12.0
Requires-Dist: pyyaml>=6.0
Requires-Dist: rank-bm25>=0.2.2
Requires-Dist: rich>=13.0
Requires-Dist: sentence-transformers>=2.2.0
Requires-Dist: torch>=2.0.0
Requires-Dist: transformers>=4.35.0
Requires-Dist: typer>=0.12.0
Requires-Dist: uvicorn>=0.32.0
Provides-Extra: client
Requires-Dist: gundog-client>=0.3.1; extra == 'client'
Provides-Extra: dev
Requires-Dist: gundog-client>=0.3.1; extra == 'dev'
Requires-Dist: pre-commit>=3.0; extra == 'dev'
Requires-Dist: pyright>=1.1; extra == 'dev'
Requires-Dist: pytest-bdd>=7.0; extra == 'dev'
Requires-Dist: pytest-cov>=4.0; extra == 'dev'
Requires-Dist: pytest>=8.0; extra == 'dev'
Requires-Dist: python-semantic-release>=9.0; extra == 'dev'
Requires-Dist: ruff>=0.8; extra == 'dev'
Requires-Dist: tox-uv>=1.0; extra == 'dev'
Requires-Dist: tox>=4.0; extra == 'dev'
